_quickjs.cpython-312-x86_64-linux-gnu.so
quickjs/__init__.py
quickjs_py-1.20.1.dist-info/METADATA
quickjs_py-1.20.1.dist-info/WHEEL
quickjs_py-1.20.1.dist-info/top_level.txt
quickjs_py-1.20.1.dist-info/RECORD
quickjs_py-1.20.1.dist-info/licenses/LICENSE
