Metadata-Version: 2.4
Name: quickjs-py
Version: 1.20.1
Summary: Wrapping the quickjs C library. (Fork of PetterS/quickjs)
Home-page: https://github.com/yuikns/quickjs-py
Author: Petter Strandmark
Author-email: petter.strandmark@gmail.com
Maintainer: Quentin Wenger
Maintainer-email: matpi@protonmail.ch
License: MIT
License-File: LICENSE
Dynamic: author
Dynamic: author-email
Dynamic: description
Dynamic: home-page
Dynamic: license
Dynamic: license-file
Dynamic: maintainer
Dynamic: maintainer-email
Dynamic: summary
